waveflowdb_client/__init__.py
waveflowdb_client/client.py
waveflowdb_client/config.py
waveflowdb_client/exceptions.py
waveflowdb_client/models.py
waveflowdb_client/utils.py
waveflowdb_client-1.0.0.dist-info/licenses/LICENSE
waveflowdb_client-1.0.0.dist-info/METADATA
waveflowdb_client-1.0.0.dist-info/WHEEL
waveflowdb_client-1.0.0.dist-info/top_level.txt
waveflowdb_client-1.0.0.dist-info/RECORD
