Metadata-Version: 2.4
Name: waveflowdb_client
Version: 1.0.0
Summary: VectorLake SDK — Deterministic backend engine powering agent workflows
Author-email: "agentanalytics.ai" <nitin@agentanalytics.ai>
License: MIT License
Project-URL: Homepage, https://agentanalytics.ai
Project-URL: Documentation, https://www.agentanalytics.ai/docs/waveflow-db
Keywords: vector db,VECTOR QUERY LANGUAGE,waveflowdb,agentanalytics,VQL
Requires-Python: >=3.8
License-File: LICENSE
Requires-Dist: requests
Requires-Dist: numpy
Requires-Dist: tqdm
Dynamic: license-file
